README.md
setup.cfg
setup.py
refgene_parser/__init__.py
refgene_parser/_refgene.py
refgene_parser.egg-info/PKG-INFO
refgene_parser.egg-info/SOURCES.txt
refgene_parser.egg-info/dependency_links.txt
refgene_parser.egg-info/top_level.txt
refgene_parser.egg-info/zip-safe