Metadata-Version: 1.1
Name: refgene-parser
Version: 0.0.1
Summary: Quickly parse genes and exons from a RefGene file
Home-page: https://github.com/clintval/refgene-parser
Author: clintval
Author-email: valentine.clint@gmail.com
License: MIT License
Download-URL: https://github.com/clintval/refgene-parser/archive/0.0.1.tar.gz
Keywords: refgene parser bioinformatics
Platform: UNKNOWN
